energypylinear/__init__.py
energypylinear/accounting/__init__.py
energypylinear/accounting/accounting.py
energypylinear/assets/__init__.py
energypylinear/assets/asset.py
energypylinear/assets/battery.py
energypylinear/assets/boiler.py
energypylinear/assets/chp.py
energypylinear/assets/evs.py
energypylinear/assets/heat_pump.py
energypylinear/assets/renewable_generator.py
energypylinear/assets/site.py
energypylinear/assets/spill.py
energypylinear/assets/valve.py
energypylinear/constraints.py
energypylinear/data_generation.py
energypylinear/debug.py
energypylinear/defaults.py
energypylinear/flags.py
energypylinear/freq.py
energypylinear/interval_data.py
energypylinear/logger.py
energypylinear/objectives.py
energypylinear/optimizer.py
energypylinear/plot.py
energypylinear/results/__init__.py
energypylinear/results/checks.py
energypylinear/results/extract.py
energypylinear/results/schema.py
energypylinear/results/warnings.py
energypylinear/utils.py
energypylinear-1.4.0.dist-info/LICENSE
energypylinear-1.4.0.dist-info/METADATA
energypylinear-1.4.0.dist-info/WHEEL
energypylinear-1.4.0.dist-info/RECORD
