Metadata-Version: 2.1
Name: energypylinear
Version: 1.4.0
Summary: Optimizing energy assets with mixed-integer linear programming.
License: GNU GPLv3
Author: Adam Green
Author-email: adam.green@adgefficiency.com
Requires-Python: >=3.10,<3.13
Classifier: License :: Other/Proprietary License
Classifier: Programming Language :: Python :: 3
Classifier: Programming Language :: Python :: 3.10
Classifier: Programming Language :: Python :: 3.11
Classifier: Programming Language :: Python :: 3.12
Requires-Dist: PuLP (>=2.7.0,<3.0.0)
Requires-Dist: markdown-include (>=0.8.1,<0.9.0)
Requires-Dist: matplotlib (>=3.6.2,<4.0.0)
Requires-Dist: numpy (>=1.26,<2.0)
Requires-Dist: pandas (>=2.0,<3.0)
Requires-Dist: pandera (>=0.14.5,<0.15.0)
Requires-Dist: pydantic (>=2.0,<3.0)
Requires-Dist: rich (>=12.0.0,<13.0.0)
Requires-Dist: seaborn (>=0.12.2,<0.13.0)
